auriga/__init__.py
auriga/auriga.pt
auriga/auriga.py
auriga/test/test.csv
auriga/test/test.fits
Auriga-1.1.dist-info/LICENSE
Auriga-1.1.dist-info/METADATA
Auriga-1.1.dist-info/WHEEL
Auriga-1.1.dist-info/entry_points.txt
Auriga-1.1.dist-info/top_level.txt
Auriga-1.1.dist-info/RECORD
