Metadata-Version: 2.1
Name: Auriga
Version: 1.1
Summary: A neural network for structure parameter determination
Home-page: https://github.com/mkounkel/Auriga
Author: Marina Kounkel
Author-email: marina.kounkel@unf.edu
Classifier: Programming Language :: Python :: 3
Classifier: License :: OSI Approved :: MIT License
Classifier: Operating System :: OS Independent
Requires-Python: >=3.6
License-File: LICENSE
Requires-Dist: torch
Requires-Dist: torchvision
Requires-Dist: astropy
Requires-Dist: astroquery
Requires-Dist: pandas
